README.md
clouds/__init__.py
clouds/base/__init__.py
clouds/base/model.py
clouds/base/player.py
clouds/game.py
clouds/main.py
clouds/sample_ai/__init__.py
clouds/sample_ai/basic.py
clouds/samples.py
clouds/visualization.py
clouds_game-0.1.2.dist-info/METADATA
clouds_game-0.1.2.dist-info/WHEEL
clouds_game-0.1.2.dist-info/RECORD
