Metadata-Version: 2.1
Name: clouds-game
Version: 0.1.2
Summary: Mission planning simulation game to reduce cloud coverage of Earth observation satellite missions
Author: Sven Prüfer
Author-email: sven.pruefer@dlr.de
Requires-Python: >=3.11,<4
Classifier: Operating System :: OS Independent
Classifier: Programming Language :: Python :: 3
Classifier: Programming Language :: Python :: 3.11
Classifier: Programming Language :: Python :: 3.12
Requires-Dist: click (>=8.1.7)
Requires-Dist: immutables (>=0.20)
Requires-Dist: pygame (>=2.6.0)
